LICENSE
MANIFEST.in
NOTICE
README.md
setup.cfg
setup.py
rocketmq/__init__.py
rocketmq/client.py
rocketmq/consts.py
rocketmq/exceptions.py
rocketmq/ffi.py
rocketmq_client_python_mi.egg-info/PKG-INFO
rocketmq_client_python_mi.egg-info/SOURCES.txt
rocketmq_client_python_mi.egg-info/dependency_links.txt
rocketmq_client_python_mi.egg-info/requires.txt
rocketmq_client_python_mi.egg-info/top_level.txt
samples/__init__.py
samples/consumer.py
samples/producer.py