Metadata-Version: 2.1
Name: rocketmq-client-python-mi
Version: 1.0.2
Summary: RocketMQ Python Client
Home-page: UNKNOWN
Author: apache.rocketmq
Author-email: dev@rocketmq.apache.org
License: UNKNOWN
Keywords: rocketmq
Platform: UNKNOWN
Classifier: Operating System :: MacOS
Classifier: Operating System :: POSIX
Classifier: Operating System :: POSIX :: Linux
Classifier: Programming Language :: Python
Classifier: Programming Language :: Python :: 2.7
Classifier: Programming Language :: Python :: 3.5
Classifier: Programming Language :: Python :: 3.6
Classifier: Programming Language :: Python :: 3.7
Classifier: Programming Language :: Python :: Implementation :: CPython
License-File: LICENSE
License-File: NOTICE
